cocotbpynq/__init__.py
cocotbpynq/buffer.py
cocotbpynq/dma.py
cocotbpynq/dut.py
cocotbpynq/mmio.py
cocotbpynq/overlay.py
cocotbpynq/simulator.py
cocotbpynq/sample/__main__.py
cocotbpynq/sample/adapted.py
cocotbpynq/sample/cocotb_runner.py
cocotbpynq/sample/original.py
cocotbpynq/sample/poly_AXILiteS_s_axi.v
cocotbpynq/sample/poly_axi.v
cocotbpynq/sample/sample.hwh
cocotbpynq-0.0.3.dist-info/licenses/COPYING
cocotbpynq-0.0.3.dist-info/METADATA
cocotbpynq-0.0.3.dist-info/WHEEL
cocotbpynq-0.0.3.dist-info/top_level.txt
cocotbpynq-0.0.3.dist-info/RECORD
