Metadata-Version: 2.4
Name: cocotbpynq
Version: 0.0.3
Summary: A direct substition for PYNQ library, to seamlessly allow simulation of PL region + PS-PL interface
Author-email: Gavin Lusby <gdplusby@uwaterloo.ca>, Nachiket Kapre <nachiket@uwaterloo.ca>
License-Expression: GPL-3.0-or-later
License-File: COPYING
Requires-Dist: numpy
Requires-Dist: cocotb
Dynamic: license-file
